bpq/__init__.py
bpq/cli.py
bpq/client.py
bpq-1.1.0.dist-info/LICENSE
bpq-1.1.0.dist-info/METADATA
bpq-1.1.0.dist-info/WHEEL
bpq-1.1.0.dist-info/entry_points.txt
bpq-1.1.0.dist-info/top_level.txt
bpq-1.1.0.dist-info/RECORD
