Metadata-Version: 2.1
Name: bpq
Version: 1.1.0
Summary: Tools that help you interact with the Bad Packets Cyber Threat Intelligence API.
Home-page: https://github.com/badpacketsllc/bpq/
Author: Mathew Woodyard
Maintainer: Mathew Woodyard
License: Apache License 2.0
Keywords: api,cti,sdk
Classifier: Programming Language :: Python :: 3
Classifier: Programming Language :: Python :: 3.6
Classifier: Programming Language :: Python :: 3.7
Classifier: Programming Language :: Python :: 3.8
Classifier: Programming Language :: Python :: 3.9
Classifier: Programming Language :: Python :: 3 :: Only
Classifier: Topic :: Internet :: WWW/HTTP
Classifier: Topic :: Software Development
Classifier: Topic :: Software Development :: Libraries
Classifier: Operating System :: MacOS :: MacOS X
Classifier: Operating System :: POSIX
Classifier: Operating System :: POSIX :: Linux
Requires-Python: >=3.6
License-File: LICENSE
